{
    "$schema": "https://schema.management.azure.com/schemas/2019-04-01/deploymentParameters.json#",
    "contentVersion": "1.0.0.0",
    "parameters": {
        "functionAppName": {
            "value": "MeteredBilling"
        },
        "hostingPlanName": {
            "value": "MeteredBillingServicePlan"
        },
        "workspaceName": {
            "value": "MeteredBillingLogAnalytics"
        },
        "workspaceSku": {
            "value": "Free"
        },
        "storageAccountName": {
            "value": "meteredbillingstore"
        },
        "eventHubsNamespace":{
            "value": "MeteredBillingEventHubs"
        },
        "eventHubName":{
            "value": "Events"
        },
        "consumerGroupName":{
            "value": "azurefunction"
        }
    }
}